x2py/__init__.py
x2py/binding.py
x2py/buffer_transform.py
x2py/builtin_events.py
x2py/case.py
x2py/cell.py
x2py/config.py
x2py/coroutine.py
x2py/deserializer.py
x2py/event.py
x2py/event_factory.py
x2py/event_queue.py
x2py/event_sink.py
x2py/fingerprint.py
x2py/flow.py
x2py/hub.py
x2py/link.py
x2py/serializer.py
x2py/flows/__init__.py
x2py/flows/event_based_flow.py
x2py/flows/frame_based_flow.py
x2py/flows/multi_thread_flow.py
x2py/flows/single_thread_flow.py
x2py/flows/threadless_flow.py
x2py/flows/time_flow.py
x2py/links/__init__.py
x2py/links/client_link.py
x2py/links/link_events.py
x2py/links/link_session.py
x2py/links/server_link.py
x2py/links/session_based_link.py
x2py/links/strategy.py
x2py/links/asyncio/__init__.py
x2py/links/asyncio/tcp_client.py
x2py/links/asyncio/tcp_server.py
x2py/links/asyncio/tcp_session.py
x2py/links/asyncore/__init__.py
x2py/links/asyncore/tcp_client.py
x2py/links/asyncore/tcp_server.py
x2py/links/asyncore/tcp_session.py
x2py/transforms/__init__.py
x2py/transforms/block_cipher.py
x2py/transforms/inverse.py
x2py/util/__init__.py
x2py/util/atomic.py
x2py/util/hash.py
x2py/util/ranged_int_pool.py
x2py/util/rwlock.py
x2py/util/trace.py
x2py/yields/__init__.py
x2py/yields/wait_for_completion.py
x2py/yields/wait_for_event.py
x2py/yields/wait_for_next.py
x2py/yields/wait_for_seconds.py
x2py/yields/wait_handle_pool.py
x2py-0.4.3.data/scripts/x2py.xpiler.py
xpiler/__init__.py
xpiler/__main__.py
xpiler/definition.py
xpiler/formatter.py
xpiler/handler.py
xpiler/main.py
xpiler/options.py
xpiler/python3_formatter.py
xpiler/types_.py
xpiler/xml_handler.py
x2py-0.4.3.dist-info/LICENSE
x2py-0.4.3.dist-info/METADATA
x2py-0.4.3.dist-info/WHEEL
x2py-0.4.3.dist-info/top_level.txt
x2py-0.4.3.dist-info/RECORD
