Metadata-Version: 2.1
Name: x2py
Version: 0.4.3
Summary: Python port of x2
Home-page: https://github.com/jaykang920/x2py
Author: Jae-jun Kang
Author-email: jaykang920@gmail.com
License: MIT
Platform: UNKNOWN
